Metadata-Version: 1.1
Name: vivek2dropoffnan
Version: 0.0.1
Summary: A simple package to perform basic data cleaning in EDA
Home-page: UNKNOWN
Author: Vivek Suresh Raj
Author-email: vivek.sureshraj@ucalgary.ca
License: UNKNOWN
Keywords: data cleaning
Platform: UNKNOWN
Classifier: Development Status :: 1 - Planning
Classifier: Programming Language :: Python :: 3
Classifier: License :: OSI Approved :: GNU Lesser General Public License v2 (LGPLv2)
Classifier: Operating System :: Microsoft :: Windows :: Windows 10
Classifier: Intended Audience :: Education
